{
  "slug": "what-we-treat/benzo-rehab-des-moines",
  "pageType": "condition",
  "seo": {
    "title": "Benzo Rehab in Des Moines, IA - Safe Taper & Treatment | Des Moines Wellness Center | Alcohol & Drug Rehab Iowa",
    "description": "Benzo rehab in Des Moines with safe benzodiazepine detox, tapering, and structured treatment. Most insurances accepted and same-day admissions."
  },
  "hero": {
    "eyebrow": "",
    "headline": "Benzodiazepine Addiction Treatment in Des Moines, IA",
    "subhead": "",
    "image": {
      "src": "https://desmoinesrecovery.com/wp-content/uploads/2026/05/shutterstock_2681806955-1024x683.jpg",
      "alt": "Person embracing freedom after addiction treatment at Des Moines rehab center"
    },
    "primaryCta": {
      "label": "(888) 378-2158",
      "href": "tel:+18883782158"
    },
    "secondaryCta": {
      "label": "Verify Insurance",
      "href": "/verify-insurance"
    }
  },
  "sections": [
    {
      "id": "key-facts",
      "kind": "features",
      "heading": "Benzo Rehab in Des Moines: Key Facts",
      "subheading": "",
      "body": [],
      "items": [
        {
          "title": "Medical detox with safe tapering and 24/7 supervision",
          "text": "",
          "icon": ""
        },
        {
          "title": "Residential rehab for structured, immersive care",
          "text": "",
          "icon": ""
        },
        {
          "title": "Dual diagnosis and evidence-based therapies (CBT, DBT)",
          "text": "",
          "icon": ""
        },
        {
          "title": "Step-down care with PHP and IOP to support real-world recovery",
          "text": "",
          "icon": ""
        },
        {
          "title": "Experienced clinical team with 10+ years of addiction treatment expertise",
          "text": "",
          "icon": ""
        },
        {
          "title": "Most Insurances accepted. Same-day admissions available.",
          "text": "",
          "icon": ""
        },
        {
          "title": "Located in Des Moines with easy access across Central Iowa.",
          "text": "",
          "icon": ""
        }
      ],
      "faqs": [],
      "image": {
        "src": "",
        "alt": ""
      }
    },
    {
      "id": "insurance-support",
      "kind": "prose",
      "heading": "Let Your Insurance Support Your Recovery",
      "subheading": "",
      "body": [
        "The cost of treatment should never be a barrier to the care you deserve. We are here to help you navigate your coverage so you can focus entirely on your recovery. Our team specializes in maximizing private insurance benefits to ensure your clinical stay at our Des Moines drug rehab is fully supported. Call us today to verify your benefits. 100% free."
      ],
      "items": [],
      "faqs": [],
      "image": {
        "src": "",
        "alt": ""
      }
    },
    {
      "id": "insurance-accepted",
      "kind": "insurance",
      "heading": "",
      "subheading": "",
      "body": [],
      "items": [
        {
          "title": "NYSHIP",
          "text": "",
          "icon": ""
        },
        {
          "title": "Aetna",
          "text": "",
          "icon": ""
        },
        {
          "title": "UMR",
          "text": "",
          "icon": ""
        },
        {
          "title": "First Health Network",
          "text": "",
          "icon": ""
        },
        {
          "title": "Surest",
          "text": "",
          "icon": ""
        },
        {
          "title": "Cigna",
          "text": "",
          "icon": ""
        },
        {
          "title": "Anthem",
          "text": "",
          "icon": ""
        },
        {
          "title": "Medical Mutual",
          "text": "",
          "icon": ""
        },
        {
          "title": "UnitedHealthcare (UHC)",
          "text": "",
          "icon": ""
        },
        {
          "title": "Beacon",
          "text": "",
          "icon": ""
        }
      ],
      "faqs": [],
      "image": {
        "src": "",
        "alt": ""
      }
    },
    {
      "id": "what-addiction-looks-like",
      "kind": "features",
      "heading": "What Benzodiazepine Addiction Looks Like",
      "subheading": "How dependence develops and why treatment becomes necessary",
      "body": [
        "Benzodiazepines (such as Xanax, Ativan, Valium, and Klonopin) are commonly prescribed for anxiety, panic disorders, and more. While effective short-term, they can quickly lead to tolerance and dependence, even when taken as directed. Over time, the body adapts to the drug, requiring higher doses to achieve the same effect. This often leads to loss of control, increased use, and difficulty stopping without withdrawal symptoms.",
        "Benzo addiction is not always obvious. Many individuals begin with a prescription and gradually become dependent without realizing it. When use continues despite negative effects on health or daily functioning, professional treatment is often needed. Common symptoms include:"
      ],
      "items": [
        {
          "title": "Needing higher doses to feel the same effect",
          "text": "",
          "icon": ""
        },
        {
          "title": "Using longer than prescribed",
          "text": "",
          "icon": ""
        },
        {
          "title": "Difficulty stopping or cutting back",
          "text": "",
          "icon": ""
        },
        {
          "title": "Increased anxiety without the drug",
          "text": "",
          "icon": ""
        },
        {
          "title": "Relying on benzos to function daily",
          "text": "",
          "icon": ""
        }
      ],
      "faqs": [],
      "image": {
        "src": "",
        "alt": ""
      }
    },
    {
      "id": "why-medical-detox",
      "kind": "prose",
      "heading": "Why Benzodiazepine Addiction Requires Medical Detox",
      "subheading": "Benzo withdrawal can be dangerous without proper supervision",
      "body": [
        "Benzodiazepine addiction is different from many other substances because withdrawal can be severe and, in some cases, life-threatening. According to the Substance Abuse and Mental Health Services Administration , withdrawal from sedatives like benzodiazepines can involve serious medical risks, including seizures, especially when not properly managed. This is why medical supervision is strongly recommended.",
        "Unlike some substances, benzodiazepines must typically be tapered gradually under clinical supervision. Abruptly stopping or attempting to taper alone can overwhelm the nervous system and increase the risk of dangerous symptoms. Because of these risks, medical detox is often the safest and most effective first step before starting ongoing rehab."
      ],
      "items": [],
      "faqs": [],
      "image": {
        "src": "",
        "alt": ""
      }
    },
    {
      "id": "detox-program",
      "kind": "features",
      "heading": "Managing Alcohol Withdrawal Symptoms Safely:",
      "subheading": "",
      "body": [
        "At Des Moines Wellness Center, our benzo detox program is designed to manage withdrawal safely while preparing you for ongoing treatment. We ensure you receive:"
      ],
      "items": [
        {
          "title": "24/7 medical supervision",
          "text": "To monitor symptoms and respond quickly to any complications",
          "icon": ""
        },
        {
          "title": "Gradual, clinically guided tapering",
          "text": "To reduce withdrawal risks and stabilize your system",
          "icon": ""
        },
        {
          "title": "Medication support when appropriate",
          "text": "Use of MAT when useful to manage anxiety, sleep, and discomfort",
          "icon": ""
        },
        {
          "title": "Continuous clinical assessment",
          "text": "To adjust care and ensure a safe transition into rehab",
          "icon": ""
        }
      ],
      "faqs": [],
      "image": {
        "src": "",
        "alt": ""
      }
    },
    {
      "id": "root-causes",
      "kind": "cards",
      "heading": "Treating the Root Causes of Benzo Addiction in Des Moines, Iowa",
      "subheading": "",
      "body": [
        "Medical detox is a critical first step for benzodiazepine addiction, but it only addresses physical dependence. Long-term recovery requires treating the underlying anxiety and mental health challenges that drive benzo use.",
        "Once you are stable, we transition you into structured benzo rehab programs in Des Moines where the real work begins. Our focus is on helping you build coping strategies and create lasting behavioral change. We offer:"
      ],
      "items": [
        {
          "title": "Residential Inpatient",
          "text": "Immersive Stabilization — Live at our private Des Moines facility while focusing fully on recovery. This structured program helps you step away from daily triggers, stabilize after detox, and begin addressing the underlying causes of benzodiazepine use.",
          "icon": ""
        },
        {
          "title": "Outpatient (PHP & IOP)",
          "text": "Back to Real Life — Continue treatment while living at home in Des Moines. These flexible programs provide ongoing clinical support, helping you manage anxiety, build coping skills, and maintain progress in real-world situations.",
          "icon": ""
        },
        {
          "title": "Clinical Aftercare & Alumni",
          "text": "Staying Sober Long-Term — Recovery from benzo addiction is ongoing. Our aftercare planning and alumni support help you stay connected, maintain stability, and continue building a life without dependence.",
          "icon": ""
        }
      ],
      "faqs": [],
      "image": {
        "src": "",
        "alt": ""
      }
    },
    {
      "id": "dual-diagnosis",
      "kind": "prose",
      "heading": "Dual Diagnosis Treatment for Benzo Addiction",
      "subheading": "Integrated care for addiction and mental health",
      "body": [
        "Benzodiazepine addiction is often closely linked to underlying mental health conditions such as anxiety, panic disorders, and trauma. Many individuals begin using medications like Xanax, Ativan, Valium, or Klonopin to manage symptoms, but over time this can lead to dependence and increased reliance.",
        "At Des Moines Wellness Center, our dual diagnosis treatment in Des Moines addresses both benzodiazepine addiction and co-occurring mental health conditions at the same time. Treating only the substance use without addressing anxiety or other underlying issues can make long-term recovery more difficult and increase the risk of relapse. Through evidence-based therapy and clinical support, we help you develop healthier ways to manage your emotional triggers without relying on benzodiazepines."
      ],
      "items": [],
      "faqs": [],
      "image": {
        "src": "",
        "alt": ""
      }
    },
    {
      "id": "our-approach",
      "kind": "features",
      "heading": "Our Approach to Benzo Rehab in Des Moines, Iowa",
      "subheading": "THE WAY WE HEAL benzo addiction",
      "body": [
        "At our Des Moines center, we use a structured clinical approach designed to treat both benzodiazepine dependence and the underlying mental health conditions that drive it. Our programs combine safe gradual tapering and evidence-based therapies to help you stabilize and build long-term recovery. We offer:"
      ],
      "items": [
        {
          "title": "Evidence-Based Therapies",
          "text": "We use proven approaches like CBT and DBT to help you identify triggers and replace reliance on benzodiazepines with healthier coping strategies.",
          "icon": ""
        },
        {
          "title": "Expert Clinical Staff",
          "text": "You’ll work with a dedicated team in Des Moines experienced in addiction treatment and mental health, providing structured and supportive care throughout recovery.",
          "icon": ""
        },
        {
          "title": "Medically Supervised Tapering",
          "text": "Benzo detox requires a gradual taper. Our team follows ASAM criteria to minimize withdrawal symptoms and ensure a stable detox process.",
          "icon": ""
        },
        {
          "title": "Relapse Prevention Skills",
          "text": "We focus on real-world strategies to manage anxiety, stress, and daily triggers without returning to benzodiazepine use.",
          "icon": ""
        },
        {
          "title": "Medication-Assisted Treatment (MAT)",
          "text": "When needed, we use clinically guided medications to support stabilization and reduce withdrawal-related discomfort when appropriate.",
          "icon": ""
        },
        {
          "title": "Individual & Group Therapy",
          "text": "A combination of one-on-one sessions and small group therapy helps you process challenges, build insight, and connect with others in recovery.",
          "icon": ""
        }
      ],
      "faqs": [],
      "image": {
        "src": "",
        "alt": ""
      }
    },
    {
      "id": "fmla-job-protection",
      "kind": "prose",
      "heading": "Job Protection and FMLA During Benzo Rehab",
      "subheading": "Take time for treatment without risking your employment",
      "body": [
        "Seeking treatment for benzodiazepine addiction doesn’t mean you have to put your job at risk. Many individuals qualify for protection under the Family and Medical Leave Act (FMLA) , which can allow you to take time off for medical and mental health treatment while maintaining your employment.",
        "At Des Moines Wellness Center, our team can help guide you through the process and provide the documentation needed for FMLA when appropriate. This allows you to focus on detox and rehab without the added stress of work obligations. Taking time to address benzo dependence is an important step toward long-term stability, and job protection options can make that decision easier."
      ],
      "items": [],
      "faqs": [],
      "image": {
        "src": "",
        "alt": ""
      }
    },
    {
      "id": "getting-to-treatment",
      "kind": "prose",
      "heading": "Getting to Treatment in Des Moines, Iowa",
      "subheading": "Easy, accessible admissions",
      "body": [
        "At Des Moines Wellness Center, we make the admissions process as simple and accessible as possible so you can focus on getting help. Our facility is conveniently located in the Des Moines area with easy access from I-35, I-80, and I-235, and just a short drive from Des Moines International Airport. Whether you’re coming from within Iowa or traveling from out of state, we make starting treatment straightforward.",
        "We can help coordinate travel and arrange airport pick-ups, so you’re not navigating this process on your own. From helping you plan your trip to coordinating your arrival time, our team stays in touch every step of the way. When you arrive, we can meet you at the airport and bring you directly to the facility, making the transition into care as smooth and stress-free as possible."
      ],
      "items": [],
      "faqs": [],
      "image": {
        "src": "",
        "alt": ""
      }
    },
    {
      "id": "medical-reviewer",
      "kind": "team-bio",
      "heading": "Medically Reviewed By Wesley Starlin, LMHC",
      "subheading": "",
      "body": [
        "Wesley Starlin is the Executive Director at Des Moines Wellness Center with over 15 years of experience in behavioral health and addiction treatment."
      ],
      "items": [],
      "faqs": [],
      "image": {
        "src": "https://desmoinesrecovery.com/wp-content/uploads/2026/06/wes-1.png",
        "alt": "Wesley Starlin - Executive Director"
      }
    },
    {
      "id": "were-here-to-listen",
      "kind": "cta",
      "heading": "We’re Here to Listen When You’re Ready",
      "subheading": "",
      "body": [
        "Taking the first step is often the hardest, but you don’t have to do it by yourself. Whether you have a quick question about our Des Moines rehab or just need to hear a supportive voice, our team is available 24/7. We provide a safe, confidential space to discuss your options, verify your private insurance, and help you find the right path forward."
      ],
      "items": [],
      "faqs": [],
      "image": {
        "src": "",
        "alt": ""
      }
    },
    {
      "id": "benzo-rehab-detox-overview",
      "kind": "prose",
      "heading": "Benzo Rehab and Detox in Des Moines, Iowa",
      "subheading": "Get safe, medically supervised treatment for benzodiazepine addiction",
      "body": [
        "If you’re searching for benzo rehab in Des Moines or broader Iowa, finding the right level of care is critical. Benzodiazepine dependence requires a structured, medically supervised approach, especially during withdrawal, when symptoms can become severe without proper support. At Des Moines Wellness Center, we provide medical detox and full-spectrum benzo rehab in Des Moines, IA, helping individuals safely taper off benzodiazepines and transition into ongoing treatment. From initial stabilization through residential care, outpatient programs, and aftercare planning, our programs are designed to support long-term recovery at every stage.",
        "As part of Quadrant Health Group , our care is backed by over 10 years of experience in addiction treatment across multiple facilities in the United States. This allows us to combine proven clinical standards, structured programming, and experienced staff with a personalized approach to care in Des Moines. Our team specializes in treating addiction to medications like Xanax, Ativan, Valium, and Klonopin, with a strong focus on dual diagnosis care for anxiety and related mental health conditions.",
        "Located in Des Moines and serving communities across Iowa, our facility offers accessible care with easy access from I-35, I-80, and I-235, and close to Des Moines International Airport, making admissions and travel more convenient for both local and out-of-state clients. We accept most insurances and offer same-day admissions when necessary. If you or a loved one needs benzodiazepine addiction treatment in Des Moines, our team is here to help. Call now to speak with an admissions specialist or verify your insurance to get started."
      ],
      "items": [],
      "faqs": [],
      "image": {
        "src": "",
        "alt": ""
      }
    },
    {
      "id": "start-recovery",
      "kind": "cta",
      "heading": "Let’s Build a Life You Don’t Need to Escape",
      "subheading": "START Your Recovery Today",
      "body": [
        "Don’t let the weight of addiction decide your future. Whether you are seeking help for yourself or a loved one, our Des Moines admissions team is ready to provide the direct answers you need to move forward. We conduct a professional clinical assessment to find the best program for your needs while securing your private insurance benefits and job protection. Fill out the form below to get started, and a member of the team will reach out shortly."
      ],
      "items": [],
      "faqs": [],
      "image": {
        "src": "",
        "alt": ""
      }
    }
  ],
  "images": [
    {
      "src": "https://desmoinesrecovery.com/wp-content/uploads/2026/05/shutterstock_2681806955-1024x683.jpg",
      "alt": "Person embracing freedom after addiction treatment at Des Moines rehab center",
      "role": "hero"
    },
    {
      "src": "https://desmoinesrecovery.com/wp-content/uploads/2026/04/goldseal_national-1-scaled-1-1-1-1024x1024.png",
      "alt": "",
      "role": "other"
    },
    {
      "src": "https://desmoinesrecovery.com/wp-content/uploads/2026/04/legit-script-certified_9eead42e-ecae-4ef3-b52d-82412e0e9e42-1-1-1.webp",
      "alt": "",
      "role": "other"
    },
    {
      "src": "https://desmoinesrecovery.com/wp-content/uploads/2026/04/NYSHIP-Logo-White-1.png",
      "alt": "NYSHIP-Logo-White.png",
      "role": "logo"
    },
    {
      "src": "https://desmoinesrecovery.com/wp-content/uploads/2026/04/mcr-aetna-white-2.webp",
      "alt": "mcr-aetna-white.webp",
      "role": "logo"
    },
    {
      "src": "https://desmoinesrecovery.com/wp-content/uploads/2026/04/UMR-Logo-White-1.png",
      "alt": "UMR-Logo-White.png",
      "role": "logo"
    },
    {
      "src": "https://desmoinesrecovery.com/wp-content/uploads/2026/04/mcr-first-health-network-white-2.webp",
      "alt": "mcr-first-health-network-white.webp",
      "role": "logo"
    },
    {
      "src": "https://desmoinesrecovery.com/wp-content/uploads/2026/04/Surest-Logo-White-1.png",
      "alt": "Surest-Logo-White.png",
      "role": "logo"
    },
    {
      "src": "https://desmoinesrecovery.com/wp-content/uploads/2026/04/cigna-white-2.webp",
      "alt": "cigna-white.webp",
      "role": "logo"
    },
    {
      "src": "https://desmoinesrecovery.com/wp-content/uploads/2026/04/anthem-white-2.webp",
      "alt": "anthem-white.webp",
      "role": "logo"
    },
    {
      "src": "https://desmoinesrecovery.com/wp-content/uploads/2026/04/med-mutual-white-2.webp",
      "alt": "med-mutual-white.webp",
      "role": "logo"
    },
    {
      "src": "https://desmoinesrecovery.com/wp-content/uploads/2026/04/mcr-uhc-white-2.webp",
      "alt": "mcr-uhc-white.webp",
      "role": "logo"
    },
    {
      "src": "https://desmoinesrecovery.com/wp-content/uploads/2026/04/mcr-beacon-white-2.webp",
      "alt": "mcr-beacon-white.webp",
      "role": "logo"
    },
    {
      "src": "https://desmoinesrecovery.com/wp-content/uploads/2026/06/wes-1.png",
      "alt": "Wesley Starlin - Executive Director",
      "role": "section"
    }
  ],
  "ctas": [
    {
      "label": "(888) 378-2158",
      "href": "tel:+18883782158"
    },
    {
      "label": "Verify Insurance",
      "href": "/verify-insurance"
    },
    {
      "label": "Verify Your Insurance",
      "href": "/admissions"
    },
    {
      "label": "Read The Bio",
      "href": "/welsey-starlin"
    }
  ]
}
